katharos/__init__.py
katharos/algebra/__init__.py
katharos/algebra/applicative/__init__.py
katharos/algebra/applicative/applicative.py
katharos/algebra/functor/__init__.py
katharos/algebra/functor/functor.py
katharos/algebra/monad/__init__.py
katharos/algebra/monad/monad.py
katharos/algebra/monoid/__init__.py
katharos/algebra/monoid/monoid.py
katharos/algebra/semigroup/__init__.py
katharos/algebra/semigroup/semigroup.py
katharos/ds/__init__.py
katharos/ds/list/__init__.py
katharos/ds/list/base_immutable_list.py
katharos/ds/list/immutable_list.py
katharos/ds/list/non_empty_list.py
katharos/ds/maybe/__init__.py
katharos/ds/maybe/maybe.py
katharos/ds/maybe/monoid_maybe.py
katharos/ds/monoid/__init__.py
katharos/ds/monoid/additive_monoid.py
katharos/ds/monoid/multiplicative_monoid.py
katharos/ds/monoid/product.py
katharos/ds/monoid/sum.py
katharos/ds/result.py
katharos/ds/side_effect/__init__.py
katharos/ds/side_effect/function_with_side_effect.py
katharos/ds/side_effect/io.py
katharos/functools/__init__.py
katharos/functools/f.py
katharos-0.2.0.dist-info/WHEEL
katharos-0.2.0.dist-info/METADATA
katharos-0.2.0.dist-info/RECORD
