Metadata-Version: 2.4
Name: katharos
Version: 0.2.0
Summary: A functional programming library for Python that provides algebraic abstractions like Semigroups, Monoids, Functors, Applicatives, and Monads, along with immutable data structures to enable composable, type-safe, and side-effect-free code.
Author: Kamal
Author-email: Kamal <kamal.farahani90@gmail.com>
License-Expression: MIT
Requires-Python: >=3.13
